{
    "count": 4,
    "stories": [
        {
            "id": "a1",
            "last_updated": 1504799962,
            "user": {
                "id": "b1",
                "name": "Terasa",
                "picture": "https://randomuser.me/api/portraits/med/women/1.jpg"
            },
            "snaps_count": 7,
            "snaps": [
                {
                    "id": "c1",
                    "mime_type": "image",
                    "url": "https://r1.ilikewallpaper.net/iphone-8-wallpapers/download/35756/Sunset-Nature-Mountain-Wood-Red-Sky-Lake-iphone-8-wallpaper-ilikewallpaper_com.jpg",
                    "last_updated": "12h"
                },
                {
                    "id": "c2",
                    "mime_type": "video",
                    "url": "http://funnymp4.net/files/download/id/4170",
                    "last_updated": "11h"
                },
                {
                    "id": "c3",
                    "mime_type": "image",
                    "url": "https://i.pinimg.com/736x/a1/d4/ea/a1d4ea964c62603ec20acd16eb0e5c85.jpg",
                    "last_updated": "10h"
                },
                {
                    "id": "c4",
                    "mime_type": "video",
                    "url": "https://clips.vorwaerts-gmbh.de/big_buck_bunny.mp4",
                    "last_updated": "9h"
                },
                {
                    "id": "c5",
                    "mime_type": "video",
                    "url": "https://clips.vorwaerts-gmbh.de/big_buck_bunny.mp4",
                    "last_updated": "8h"
                },
                {
                    "id": "c6",
                    "mime_type": "image",
                    "url": "https://iphonehdwallpapers.net/wp-content/cache/76354cd2fcd65995a5f866f6bbb9ad0c_w324_h576_sc.jpg",
                    "last_updated": "7h"
                },
                {
                    "id": "c7",
                    "mime_type": "video",
                    "url": "http://funnymp4.net/files/download/id/5397",
                    "last_updated": "6h"
                }
            ]
        },
        {
            "id": "a2",
            "last_updated": 1504799962,
            "user": {
                "id": "b2",
                "name": "Nicky",
                "picture": "https://randomuser.me/api/portraits/med/women/2.jpg"
            },
            "snaps_count": 6,
            "snaps": [
                {
                    "id": "c8",
                    "mime_type": "video",
                    "url": "http://funnymp4.net/files/download/id/3466",
                    "last_updated": "1m"
                },
                {
                    "id": "c9",
                    "mime_type": "image",
                    "url": "https://static1.squarespace.com/static/5397b451e4b07f25d1682866/5643b980e4b0eaf052b84a23/5643b983e4b00c09aadce12d/1447278987246/Apple-iPhone-5-5s-Wallpaper-Good-Dino-3.jpg",
                    "last_updated": "1m"
                },
                {
                    "id": "c10",
                    "mime_type": "video",
                    "url": "https://sample-videos.com/video123/mp4/720/big_buck_bunny_720p_1mb.mp4",
                    "last_updated": "6h"
                },
                {
                    "id": "c11",
                    "mime_type": "image",
                    "url": "https://i.pinimg.com/736x/62/32/ef/6232ef50dd5b94cb97960e22c7c6dafb--galaxy-wallpaper-iphone-iphone-.jpg",
                    "last_updated": "2m"
                },
                {
                    "id": "c12",
                    "mime_type": "image",
                    "url": "https://static1.squarespace.com/static/5397b451e4b07f25d1682866/5643bc81e4b021eb442c7b72/5643bddee4b07810c0b2f749/1447280129681/Samsung-Galaxy-S5-Android-Wallpaper-Good-Dino-2.jpg",
                    "last_updated": "2m"
                },
                {
                    "id": "c13",
                    "mime_type": "image",
                    "url": "https://images.bluethumb.com.au/uploads/listing/118572/brita-lee-tiger-in-bamboo-forest-bluethumb-647f.jpg?w=800&auto=compress&cs=tinysrgb&q=70&s=b50eb51ef394a44b0d38e6fbea955159",
                    "last_updated": "2m"
                }
            ]
        },
        {
            "id": "a3",
            "last_updated": 1504799992,
            "user": {
                "id": "b2",
                "name": "Lara",
                "picture": "https://randomuser.me/api/portraits/med/women/3.jpg"
            },
            "snaps_count": 5,
            "snaps": [
                {
                    "id": "c11",
                    "mime_type": "image",
                    "url": "http://www.appleplans.co.uk/wp-content/uploads/2017/03/If-it-looks-good-and-all.jpg",
                    "last_updated": "8m"
                },
                {
                    "id": "c12",
                    "mime_type": "image",
                    "url": "https://theultralinx.com/.image/t_share/MTQxOTUxNzg4ODkwNDAwNDUy/212iphoneiphone-wallpaperswallpapers1jpg.jpg",
                    "last_updated": "9m"
                },
                {
                    "id": "c13",
                    "mime_type": "image",
                    "url": "https://hdqwalls.com/download/8-bit-pixel-art-city-2o-1280x2120.jpg",
                    "last_updated": "10m"
                },
                {
                    "id": "c14",
                    "mime_type": "image",
                    "url": "https://i-cdn.phonearena.com/images/articles/257597-image/boom.jpg",
                    "last_updated": "11m"
                },
                {
                    "id": "c15",
                    "mime_type": "image",
                    "url": "http://www.designbolts.com/wp-content/uploads/2017/04/paris-iPhone-7-Wallpaper-HD.jpg",
                    "last_updated": "12m"
                }
            ]
        },
        {
            "id": "a4",
            "last_updated": 1504799092,
            "user": {
                "id": "b2",
                "name": "Rossie",
                "picture": "https://randomuser.me/api/portraits/med/women/4.jpg",
                "last_updated": "13m"
            },
            "snaps_count": 3,
            "snaps": [
                {
                    "id": "c16",
                    "mime_type": "image",
                    "url": "https://upload.wikimedia.org/wikipedia/commons/f/f5/Steve_Jobs_Headshot_2010-CROP2.jpg",
                    "last_updated": "14m"
                },
                {
                    "id": "c17",
                    "mime_type": "image",
                    "url": "https://www.droidviews.com/wp-content/uploads/2016/09/iOS10_wall_droidviews_021.jpg",
                    "last_updated": "15m"
                },
                {
                    "id": "c18",
                    "mime_type": "image",
                    "url": "https://boygeniusreport.files.wordpress.com/2016/11/papers-co-ni07-night-drive-car-light-red-dark-34-iphone6-plus-wallpaper.jpg",
                    "last_updated": "16m"
                }
            ]
            
        }]
}
